odoo/addons/base_tier_validation/README.rst
odoo/addons/base_tier_validation/__init__.py
odoo/addons/base_tier_validation/__manifest__.py
odoo/addons/base_tier_validation/data/cron_data.xml
odoo/addons/base_tier_validation/data/mail_data.xml
odoo/addons/base_tier_validation/i18n/base_tier_validation.pot
odoo/addons/base_tier_validation/i18n/es.po
odoo/addons/base_tier_validation/i18n/es_MX.po
odoo/addons/base_tier_validation/i18n/fr.po
odoo/addons/base_tier_validation/i18n/hr.po
odoo/addons/base_tier_validation/i18n/it.po
odoo/addons/base_tier_validation/i18n/nl_NL.po
odoo/addons/base_tier_validation/i18n/pt_BR.po
odoo/addons/base_tier_validation/i18n/sk.po
odoo/addons/base_tier_validation/i18n/sk_SK.po
odoo/addons/base_tier_validation/i18n/sv.po
odoo/addons/base_tier_validation/i18n/zh_CN.po
odoo/addons/base_tier_validation/migrations/14.0.3.0.0/pre-migrate.py
odoo/addons/base_tier_validation/models/__init__.py
odoo/addons/base_tier_validation/models/res_config_settings.py
odoo/addons/base_tier_validation/models/res_users.py
odoo/addons/base_tier_validation/models/tier_definition.py
odoo/addons/base_tier_validation/models/tier_review.py
odoo/addons/base_tier_validation/models/tier_validation.py
odoo/addons/base_tier_validation/readme/CONFIGURE.rst
odoo/addons/base_tier_validation/readme/CONTRIBUTORS.rst
odoo/addons/base_tier_validation/readme/DESCRIPTION.rst
odoo/addons/base_tier_validation/readme/HISTORY.rst
odoo/addons/base_tier_validation/readme/ROADMAP.rst
odoo/addons/base_tier_validation/security/ir.model.access.csv
odoo/addons/base_tier_validation/security/tier_validation_security.xml
odoo/addons/base_tier_validation/static/description/icon.png
odoo/addons/base_tier_validation/static/description/index.html
odoo/addons/base_tier_validation/static/src/js/systray.js
odoo/addons/base_tier_validation/static/src/js/tier_review_widget.js
odoo/addons/base_tier_validation/static/src/scss/review.scss
odoo/addons/base_tier_validation/static/src/scss/systray.scss
odoo14_addon_base_tier_validation-14.0.4.1.1.dist-info/METADATA
odoo14_addon_base_tier_validation-14.0.4.1.1.dist-info/WHEEL
odoo14_addon_base_tier_validation-14.0.4.1.1.dist-info/top_level.txt
odoo14_addon_base_tier_validation-14.0.4.1.1.dist-info/RECORD
